podm/__init__.py
podm/box.py
podm/coco.py
podm/coco2lableme.py
podm/coco_decoder.py
podm/coco_encoder.py
podm/metrics.py
podm/pascal2coco.py
podm/visualize.py
object_detection_metrics-0.4.post1.dist-info/LICENSE
object_detection_metrics-0.4.post1.dist-info/METADATA
object_detection_metrics-0.4.post1.dist-info/WHEEL
object_detection_metrics-0.4.post1.dist-info/entry_points.txt
object_detection_metrics-0.4.post1.dist-info/top_level.txt
object_detection_metrics-0.4.post1.dist-info/RECORD
