Metadata-Version: 2.1
Name: object-detection-metrics
Version: 0.4.post1
Summary: Object Detection Metrics
Home-page: https://github.com/yfpeng/object_detection_metrics
Author: Yifan Peng
Author-email: yip4002@med.cornell.edu
License: MIT License
Keywords: object detection metrics
Classifier: Development Status :: 2 - Pre-Alpha
Classifier: Intended Audience :: Developers
Classifier: Intended Audience :: Science/Research
Classifier: License :: OSI Approved :: MIT License
Classifier: Operating System :: POSIX :: Linux
Classifier: Operating System :: MacOS
Classifier: Topic :: Text Processing
Classifier: Topic :: Software Development
Classifier: Topic :: Scientific/Engineering :: Artificial Intelligence
Classifier: Topic :: Scientific/Engineering :: Information Analysis
Classifier: Programming Language :: Python :: 3.7
Classifier: Programming Language :: Python :: 3.8
Classifier: Programming Language :: Python :: 3.9
Requires-Python: >=3.7
Provides-Extra: rest
License-File: LICENSE
